student_mixture/__init__.py
student_mixture/_generate_prime_list.py
student_mixture/_halton.py
student_mixture/_multivariate_t_cdf.py
student_mixture/_multivariate_t_cdf_qmc.py
student_mixture/_multivariate_t_fit_functions.py
student_mixture/_multivariate_t_functions.py
student_mixture/_student_mixture_functions.py
student_mixture/multivariate_t.py
student_mixture/multivariate_t_fit.py
student_mixture/student_mixture.py
student_mixture-0.2.0.dist-info/licenses/LICENSE
student_mixture-0.2.0.dist-info/METADATA
student_mixture-0.2.0.dist-info/WHEEL
student_mixture-0.2.0.dist-info/top_level.txt
student_mixture-0.2.0.dist-info/RECORD
