Metadata-Version: 2.4
Name: student_mixture
Version: 0.2.0
Summary: A package for fitting a Student's t-mixture model
Home-page: https://github.com/omritomer/student_mixture
Author: Omri Tomer
Author-email: omritomer1990@gmail.com
License: MIT license
Keywords: student_mixture
Classifier: Development Status :: 2 - Pre-Alpha
Classifier: Intended Audience :: Developers
Classifier: License :: OSI Approved :: MIT License
Classifier: Natural Language :: English
Classifier: Programming Language :: Python :: 3
Requires-Python: >=3.6
License-File: LICENSE
Requires-Dist: numpy>=1.17.3
Requires-Dist: scipy>=1.3.1
Requires-Dist: scikit-learn>=1.5.0
Dynamic: author
Dynamic: author-email
Dynamic: classifier
Dynamic: description
Dynamic: description-content-type
Dynamic: home-page
Dynamic: keywords
Dynamic: license
Dynamic: license-file
Dynamic: requires-dist
Dynamic: requires-python
Dynamic: summary
